[{"trial": 0, "rep": [0.0, 0.0, 0.0, 1, 1]}, {"trial": 1, "rep": [0.21, 0.0, 1.0, 1, 1]}, {"trial": 2, "rep": [0.0, 1.0, 0.0, 1, 1]}, {"trial": 3, "rep": [0.219, 1.0, 0.0, 1, 1]}, {"trial": 4, "rep": [0.008, 1.0, 0.009, 1, 1]}, {"trial": 5, "rep": [0.0, 1.0, 1.0, 1, 1]}, {"trial": 6, "rep": [0.0, 1.0, 1.0, 1, 1]}, {"trial": 7, "rep": [0.052, 0.0, 1.0, 1, 1]}, {"trial": 8, "rep": [0.664, 1.0, 0.0, 1, 1]}, {"trial": 9, "rep": [0.871, 1.0, 0.86, 1, 1]}, {"trial": 10, "rep": [0.946, 1.0, 0.026, 1, 1]}, {"trial": 11, "rep": [1.0, 1.0, 1.0, 1, 1]}, {"trial": 12, "rep": [1.0, 1.0, 1.0, 1, 1]}, {"trial": 13, "rep": [1.0, 1.0, 0.0, 1, 1]}, {"trial": 14, "rep": [1.0, 1.0, 1.0, 0, 1]}, {"trial": 15, "rep": [1.0, 1.0, 1.0, 1, 1]}, {"trial": 16, "rep": [1.0, 1.0, 0.0, 1, 1]}, {"trial": 17, "rep": [0.238, 1.0, 0.285, 0, 1]}, {"trial": 18, "rep": [1.0, 0.0, 1.0, 1, 1]}, {"trial": 19, "rep": [0.992, 1.0, 0.011, 1, 1]}, {"trial": 20, "rep": [0.132, 1.0, 0.127, 1, 1]}, {"trial": 21, "rep": [1.0, 1.0, 1.0, 0, 1]}, {"trial": 22, "rep": [0.0, 0.0, 0.0, 1, 1]}, {"trial": 23, "rep": [0.0, 0.0, 0.0, 1, 1]}, {"trial": 24, "rep": [1.0, 1.0, 0.361, 1, 1]}, {"trial": 25, "rep": [1.0, 0.0, 0.0, 1, 1]}, {"trial": 26, "rep": [0.989, 1.0, 0.014, 1, 1]}, {"trial": 27, "rep": [0.871, 1.0, 0.863, 0, 1]}, {"trial": 28, "rep": [0.018, 1.0, 0.027, 1, 1]}, {"trial": 29, "rep": [0.0, 0.0, 0.0, 1, 1]}, {"trial": 30, "rep": [0.0, 0.0, 0.0, 1, 1]}, {"trial": 31, "rep": [0.0, 0.0, 0.0, 1, 1]}]